azure/mgmt/purview/__init__.py
azure/mgmt/purview/_configuration.py
azure/mgmt/purview/_purview_management_client.py
azure/mgmt/purview/_version.py
azure/mgmt/purview/aio/__init__.py
azure/mgmt/purview/aio/_configuration.py
azure/mgmt/purview/aio/_purview_management_client.py
azure/mgmt/purview/aio/operations/__init__.py
azure/mgmt/purview/aio/operations/_accounts_operations.py
azure/mgmt/purview/aio/operations/_default_accounts_operations.py
azure/mgmt/purview/aio/operations/_operations.py
azure/mgmt/purview/aio/operations/_private_endpoint_connections_operations.py
azure/mgmt/purview/aio/operations/_private_link_resources_operations.py
azure/mgmt/purview/models/__init__.py
azure/mgmt/purview/models/_models.py
azure/mgmt/purview/models/_models_py3.py
azure/mgmt/purview/models/_purview_management_client_enums.py
azure/mgmt/purview/operations/__init__.py
azure/mgmt/purview/operations/_accounts_operations.py
azure/mgmt/purview/operations/_default_accounts_operations.py
azure/mgmt/purview/operations/_operations.py
azure/mgmt/purview/operations/_private_endpoint_connections_operations.py
azure/mgmt/purview/operations/_private_link_resources_operations.py
azure_mgmt_purview-1.0.0.dist-info/METADATA
azure_mgmt_purview-1.0.0.dist-info/WHEEL
azure_mgmt_purview-1.0.0.dist-info/top_level.txt
azure_mgmt_purview-1.0.0.dist-info/RECORD
